{
  "project_info": {
    "project_number": "325461915088",
    "project_id": "smart-schiz",
    "storage_bucket": "smart-schiz.appspot.com"
  },
  "client": [
    {
      "client_info": {
        "mobilesdk_app_id": "1:325461915088:android:a85ff1eb491128f41f35d5",
        "android_client_info": {
          "package_name": "com.zeyrex.gadgetbridge.smartschizo"
        }
      },
      "oauth_client": [],
      "api_key": [
        {
          "current_key": "AIzaSyCOhEqIuNU6WFzLoduuwP9ZpSZE-Ks_mUo"
        }
      ],
      "services": {
        "appinvite_service": {
          "other_platform_oauth_client": []
        }
      }
    }
  ],
  "configuration_version": "1"
}